MANIFEST.in
README.md
setup.py
src/vdk/plugin/lineage/openlineage_config.py
src/vdk/plugin/lineage/openlineage_utils.py
src/vdk/plugin/lineage/plugin_lineage.py
src/vdk/plugin/lineage/sql_lineage_parser.py
src/vdk/plugin/marquez/.env
src/vdk/plugin/marquez/docker-compose.yaml
src/vdk/plugin/marquez/marquez_plugin.py
src/vdk/plugin/marquez/marquez_server.py
src/vdk/plugin/marquez/docker/init-db.sh
src/vdk/plugin/marquez/docker/wait-for-it.sh
src/vdk_lineage.egg-info/PKG-INFO
src/vdk_lineage.egg-info/SOURCES.txt
src/vdk_lineage.egg-info/dependency_links.txt
src/vdk_lineage.egg-info/entry_points.txt
src/vdk_lineage.egg-info/requires.txt
src/vdk_lineage.egg-info/top_level.txt