Metadata-Version: 2.1
Name: vdk-lineage
Version: 0.3.604201902
Summary: VDK Lineage plugin collects lineage (input -> job -> output) information and send it to a pre-configured destination.
Home-page: https://github.com/vmware/versatile-data-kit
Classifier: Development Status :: 2 - Pre-Alpha
Classifier: License :: OSI Approved :: Apache Software License
Classifier: Programming Language :: Python :: 3.7
Classifier: Programming Language :: Python :: 3.8
Classifier: Programming Language :: Python :: 3.9
Classifier: Programming Language :: Python :: 3.10
